fly_online/__init__.py
fly_online/fly.py
fly_online/login.py
fly_online/ping.py
fly_online-0.0.7.dist-info/LICENSE
fly_online-0.0.7.dist-info/METADATA
fly_online-0.0.7.dist-info/WHEEL
fly_online-0.0.7.dist-info/entry_points.txt
fly_online-0.0.7.dist-info/top_level.txt
fly_online-0.0.7.dist-info/RECORD
