Metadata-Version: 2.1
Name: fly-online
Version: 0.0.7
Summary: Never get offline in NBU
Home-page: https://github.com/QiangZiBro/flyOnline
Author: QiangZiBro
Author-email: qiangzibro@gmail.com
License: UNKNOWN
Platform: UNKNOWN
Requires-Dist: selenium
Requires-Dist: geckodriver-autoinstaller
